pybasicutils/__init__.py
pybasicutils/clearScreen.py
pybasicutils/crypted.py
pybasicutils/jsoned.py
pybasicutils/maths.py
pybasicutils/sized.py
pybasicutils-1.2.0.dist-info/LICENSE
pybasicutils-1.2.0.dist-info/METADATA
pybasicutils-1.2.0.dist-info/WHEEL
pybasicutils-1.2.0.dist-info/top_level.txt
pybasicutils-1.2.0.dist-info/RECORD
