Metadata-Version: 2.1
Name: pybasicutils
Version: 1.2.0
Summary: Basic Utilities for python development.
Author: ItzSCodez1467 (Srijal Dutta)
Author-email: <srijaldutta.official+pybasicutils@gmail.com>
Keywords: python,utils,pytils,pyutils,basic utils,utilities
Classifier: Development Status :: 1 - Planning
Classifier: Intended Audience :: Developers
Classifier: Programming Language :: Python :: 3
Classifier: Operating System :: Unix
Classifier: Operating System :: MacOS :: MacOS X
Classifier: Operating System :: Microsoft :: Windows
License-File: LICENSE
Requires-Dist: cryptography
Requires-Dist: getpass
